tests/__init__.py
tests/preprocessing/__init__.py
tests/preprocessing/test_text_preprocessing.py
vn_helper/__init__.py
vn_helper/num_preprocessing/__init__.py
vn_helper/num_preprocessing/numeric.py
vn_helper/text_preprocessing/__init__.py
vn_helper/text_preprocessing/text.py
vn_helper-1.0.0.dist-info/AUTHORS.md
vn_helper-1.0.0.dist-info/LICENSE.txt
vn_helper-1.0.0.dist-info/METADATA
vn_helper-1.0.0.dist-info/WHEEL
vn_helper-1.0.0.dist-info/top_level.txt
vn_helper-1.0.0.dist-info/RECORD
